{
  "sorted_middleware": [],
  "middleware": {
    "/": {
      "files": [
        "server/edge/chunks/_3e36637b._.js",
        "server/edge/chunks/[root-of-the-server]__5e96eddc._.js",
        "server/edge/chunks/edge-wrapper_386ac0d6.js"
      ],
      "name": "middleware",
      "page": "/",
      "matchers": [
        {
          "regexp": "/:nextData(_next/data/[^/]{1,})?/:nextInternalLocale((?!_next/)[^/.]{1,})/:path*{(\\\\.json)}?",
          "originalSource": "/:path*"
        }
      ],
      "wasm": [],
      "assets": [],
      "env": {
        "__NEXT_BUILD_ID": "development",
        "NEXT_SERVER_ACTIONS_ENCRYPTION_KEY": "kQz3/lRo+UNw+4gObbRPTGpZRewTWxmIDzhOrsXpOyY=",
        "__NEXT_PREVIEW_MODE_ID": "cf44343bc30634d520ee173f34501447",
        "__NEXT_PREVIEW_MODE_ENCRYPTION_KEY": "03c93a5a0c5196c800aa4e2cd848953e8f8085723d8dd810de29e9be469aa482",
        "__NEXT_PREVIEW_MODE_SIGNING_KEY": "3e0a700c7fe5ca9abe1ebbbc96c45f5d9942610836e2e4a7b7a0b3510defb19e"
      }
    }
  },
  "instrumentation": null,
  "functions": {}
}